kmd/__init__.py
kmd/kmd.py
kmd/quoting.py
kmd/testing.py
kmd/completions/__init__.py
kmd/completions/command.py
kmd/completions/environment.py
kmd/completions/filename.py
kmd/completions/hostname.py
kmd/completions/username.py
kmd/examples/__init__.py
kmd/examples/environment.py
kmd/examples/myshell.py
kmd-2.4.dist-info/LICENSE
kmd-2.4.dist-info/METADATA
kmd-2.4.dist-info/WHEEL
kmd-2.4.dist-info/top_level.txt
kmd-2.4.dist-info/RECORD
