Metadata-Version: 2.1
Name: kmd
Version: 2.4
Summary: An interpreter framework
Home-page: https://github.com/stefanholek/kmd
Author: Stefan H. Holek
Author-email: stefan@epy.co.at
License: PSF-2.0
Project-URL: Documentation, https://kmd.readthedocs.io/en/stable/
Keywords: command line,command shell,shell,interpreter,REPL
Classifier: Development Status :: 5 - Production/Stable
Classifier: Intended Audience :: Developers
Classifier: License :: OSI Approved :: Python Software Foundation License
Classifier: Operating System :: MacOS :: MacOS X
Classifier: Operating System :: POSIX
Classifier: Programming Language :: Python
Classifier: Programming Language :: Python :: 2
Classifier: Programming Language :: Python :: 3
Classifier: Programming Language :: Python :: Implementation :: CPython
License-File: LICENSE
Requires-Dist: rl (>=3.1)
Provides-Extra: docs
Requires-Dist: sphinx (==5.3.0) ; extra == 'docs'
Requires-Dist: sphinx-rtd-theme (==1.0.0) ; extra == 'docs'
